MANIFEST.in
setup.cfg
setup.py
stratus_api/auth/__init__.py
stratus_api/auth/jwt.py
stratus_api/auth/oauth.py
stratus_api/auth/schemas/auth.yaml
stratus_api_auth.egg-info/PKG-INFO
stratus_api_auth.egg-info/SOURCES.txt
stratus_api_auth.egg-info/dependency_links.txt
stratus_api_auth.egg-info/requires.txt
stratus_api_auth.egg-info/top_level.txt