Metadata-Version: 2.1
Name: stratus-api-auth
Version: 0.0.6
Summary: An API framework for simplified OAuth
Home-page: https://bitbucket.org/adarainc/stratus-api-auth
Author: DOT
Author-email: dot@adara.com
Classifier: Programming Language :: Python :: 3
Classifier: License :: OSI Approved :: MIT License
Classifier: Operating System :: OS Independent
Requires-Python: >=3.11
